{
    "first_name": "Laura",
    "last_name": "Bianchi",
    "access_mode": "ambulance",
    "birth_date": "March 12, 1985",
    "birth_place": "Florence",
    "age": "40",
    "gender": "female",
    "residence_city": "Rome",
    "residence_address": "via Appia 205",
    "phone": "061234567",
    "skin_state": "normal",
    "consciousness_state": "conscious",
    "pupils_state": "ischoric and reactive",
    "respiratory_state": "difficulty breathing",
    "history": "",
    "medications_taken": "",
    "symptoms": "chest pain and difficulty breathing",
    "heart_rate": "98 bpm",
    "oxygenation": "94%",
    "blood_pressure": "125-85 mmHg",
    "temperature": "37.0 °C",
    "blood_glucose": "102 mg per dl",
    "medical_actions": "analgesic therapy and observation in the trauma unit",
    "assessment": "possible rib fracture",
    "plan": "observation in the trauma unit",
    "triage_code": "yellow"
}